verify4py/Issuer.py
verify4py/JsonIssuer.py
verify4py/PdfIssuer.py
verify4py/UniversityDiplomaIssuer.py
verify4py/__init__.py
verify4py/certify_sc_utils.py
verify4py/json_utils.py
verify4py/pdf.py
verify4py/test_UniversityDiplomaIssuer.py
verify4py/university_abi.py
verify4py/utils.py
verify4py-2.0.5.dist-info/LICENSE
verify4py-2.0.5.dist-info/METADATA
verify4py-2.0.5.dist-info/WHEEL
verify4py-2.0.5.dist-info/top_level.txt
verify4py-2.0.5.dist-info/RECORD
