Metadata-Version: 2.1
Name: verify4py
Version: 2.0.5
Summary: Issue certificates using blockchain and smart contract
Home-page: https://github.com/teo-mn/verify4py
Author: Surenbayar Doloonjin
Author-email: surenbayar@corex.mn
Project-URL: Bug Tracker, https://github.com/teo-mn/verify4py/issues
Classifier: Programming Language :: Python :: 3
Classifier: License :: OSI Approved :: MIT License
Classifier: Operating System :: OS Independent
Requires-Python: >=3.6
License-File: LICENSE
Requires-Dist: web3 ==6.6.1
Requires-Dist: pdfrw ==0.3
